{
    "cover": "https://pic3.zhimg.com/4c482955e702ea7f52ba33ab8a7cf6ea.jpg",
    "count": 5,
    "jokes": [
        {
            "title": "怎么定义「想清楚了」？",
            "author": "水木丁",
            "bio": "",
            "imgs": [],
            "content": "「想清楚了」就是以后出了什么问题你只能找个没人的地方抽自己，再也不能抱怨别人了"
        },
        {
            "title": "哪本书（非小说类）的第一句话吸引着你一直读了下去？",
            "author": "匿名用户",
            "bio": "",
            "imgs": [],
            "content": "本习题集为内部资料，请勿大范围传阅。。。"
        },
        {
            "title": "你遇到过哪些小概率事件？",
            "author": "斑陀螺",
            "bio": "纱布互联网从业者 & 死动漫迷",
            "imgs": [],
            "content": "我成功取消了一次打印任务。"
        },
        {
            "title": "iPod touch 存在的意义是什么？",
            "author": "王维东",
            "bio": "福建星网视易数字娱乐产品经理",
            "imgs": [],
            "content": "其终极意义是作为历年年终抽奖奖品的一部分：\r\n特等奖：MacBook Air\r\n一等奖：iPhone 5s\r\n二等奖：iPad\r\n三等奖：iPod Touch"
        },
        {
            "title": "光棍怎么过圣诞节？",
            "author": "徐红",
            "bio": "做不好，所以疯狂的猜想和补脑。。。。。",
            "imgs": [],
            "content": "复习呀，难道你还想年也过不好吗？╰_╯"
        }
    ]
}