{
    "cover": "https://pic2.zhimg.com/9c9307fdc51832acb1602a17978bd18d.jpg",
    "count": 4,
    "jokes": [
        {
            "title": "为什么程序员无论到哪儿都喜欢背电脑包，哪怕里面没有装电脑？",
            "author": "Cascade",
            "bio": "",
            "imgs": [],
            "content": "> "
        },
        {
            "title": "萝莉御姐都喜欢大叔，因为大叔身上有让人安心的味道。可是大叔心里到底是怎么想的呢？",
            "author": "知乎用户",
            "bio": "流氓，黑前女友综合症，.NET、Web、UX，摄影，吉他，健身，烘焙，18cm",
            "imgs": [],
            "content": "> "
        },
        {
            "title": "「没本事的男人才会指责女人现实」这句话如何反驳？",
            "author": "刘念",
            "bio": "网名“泳湿小狗”，追女孩教练，蛋糕店老板。",
            "imgs": [],
            "content": "> "
        },
        {
            "title": "有些老人为什么要诬陷扶他们起来的人？",
            "author": "易俊杰",
            "bio": "",
            "imgs": [],
            "content": "> "
        }
    ]
}