{
    "cover": "https://pic2.zhimg.com/c10761381b5a7b71cdb369d1ead055c5.jpg",
    "count": 4,
    "jokes": [
        {
            "title": "如何承认女朋友错误的观点是正确的？",
            "author": "知乎用户",
            "bio": "进击的主妇",
            "imgs": [],
            "content": "跪着说"
        },
        {
            "title": "当女生问「我和 xx 比哪个更漂亮」怎么回答好？",
            "author": "nonolyli",
            "bio": "。",
            "imgs": [],
            "content": "魔镜犯了一个错误，最后它碎了。"
        },
        {
            "title": "就明清两朝比较而言，为何明朝皇帝多昏庸无能，清朝皇帝多励精图治？",
            "author": "hiheng",
            "bio": "做人如果没有梦想，那跟咸鱼有什么区别？",
            "imgs": [],
            "content": "我们看到的《明史》，是由清朝几代皇帝呕心沥血、煞费苦心修订的。"
        },
        {
            "title": "大姨妈来了能吃披萨吗？",
            "author": "匿名用户",
            "bio": "",
            "imgs": [],
            "content": "岁数大的人一般吃不惯这个。他们不习惯芝士。"
        }
    ]
}