{
    "cover": "http://pic3.zhimg.com/5612e88c595a0dd754803cf570a43c9c.jpg",
    "count": 4,
    "jokes": [
        {
            "title": "如何看待现在部分女大学生在爱情方面很「现实」的现象？",
            "author": "王若鱼",
            "bio": "莫问前程",
            "imgs": [],
            "content": "现实点的妹子好呀，不现实的妹子都看脸。"
        },
        {
            "title": "自己一个人看鬼片或剧情片会非常容易害怕，怎么解决？",
            "author": "焚香夜",
            "bio": "哲学烟酒生在读",
            "imgs": [],
            "content": "关掉音效，打开猪八戒背媳妇单曲循环。"
        },
        {
            "title": "遇到女孩求六元回家路费这种情况，怎么做才好？",
            "author": "朱嘟嘟嘟嘟",
            "bio": "大 波 浪",
            "imgs": [],
            "content": "「出门带粉笔的人，通常运气都不会太好。」"
        },
        {
            "title": "国内外影坛有哪些有大师潜质的新生代导演？",
            "author": "岳豪",
            "bio": "电影声音创作/游戏音频设计/高贵的器材党",
            "imgs": [],
            "content": "才没有「大师潜质」这种东西呢。\r\n他们都是在导演成为大师之后才说：“XXX 在他的处女作中就表现出了成为大师的潜质。”"
        }
    ]
}