{
    "cover": "http://pic4.zhimg.com/0e0865e815327fb0d3cbdc90e9728db3.jpg",
    "count": 4,
    "jokes": [
        {
            "title": "要求未来的男朋友把我指定的书、电影和电视剧看一遍，然后写 80 万字观后感，过分吗？",
            "author": "护士衫下",
            "bio": "世界の中心で、愛を避ける。",
            "imgs": [],
            "content": "题主，我们国家是不允许私人申请开设博士点的。"
        },
        {
            "title": "有哪些像《神探夏洛克》的颜值和剧情都好看的剧?",
            "author": "知乎用户",
            "bio": "鲜嫩多汁。",
            "imgs": [],
            "content": "第一次听说有人看夏洛克是冲着颜值去的，既然如此，那我推荐你看《非常 6+1》。"
        },
        {
            "title": "怎么看待《盗墓笔记》电视剧将「盗墓」改为「护宝」？",
            "author": "钱庄庄",
            "bio": "祖传修眉，天生电子杀手，失眠大师。",
            "imgs": [],
            "content": "《护宝笔记》不够雅，也与剧情不符，建议改成和“盗墓”读音相近且与剧情相关的词汇，\r\n如《耽美笔记》。"
        },
        {
            "title": "如何看待 ISIS 恐怖分子在 Twitter 上被日本动漫宅骚扰以至于删号？",
            "author": "知乎用户",
            "bio": "什么都懂一点，什么都不懂。",
            "imgs": [],
            "content": "这让我想起了《哈利波特》里面的情节。\r\n博格特是一种变形的生物，它会看透你的内心，变成你最害怕的东西，而对付他最好的办法就是大笑。\r\n而这些日本网民所做的是一样的事情。"
        }
    ]
}