{
    "cover": "http://pic1.zhimg.com/6ad240f2fe04ef9728f60ee9fcc1b5ec.jpg",
    "count": 4,
    "jokes": [
        {
            "title": "为什么合租时总是看见「限女生」，为什么？真是不明白什么社会了，还这么封建，能吃多大亏咋的，女孩子就应该多跟男生接触嘛，难道跟女生结婚吗？",
            "author": "穆杨",
            "bio": "",
            "imgs": [],
            "content": "> 题主这个逻辑，我觉得「限女生」是非常正确的。"
        },
        {
            "title": "女人是不是碰到甜言蜜语就会变得不清醒？",
            "author": "匿名用户",
            "bio": "",
            "imgs": [],
            "content": "> "
        },
        {
            "title": "俗话说「男人的头女人的腰不能乱摸」是为什么？",
            "author": "匿名用户",
            "bio": "",
            "imgs": [],
            "content": "> "
        },
        {
            "title": "科学和迷信的分界点是哪里？",
            "author": "匿名用户",
            "bio": "",
            "imgs": [],
            "content": "> 分界点是「我错了」。"
        }
    ]
}