{
    "cover": "http://pic4.zhimg.com/98391df38dc03d07253b236eeaf88a7b.jpg",
    "count": 4,
    "jokes": [
        {
            "title": "如何评价因为舍友喝了他一杯水就生气的人呢？",
            "author": "刘新新",
            "bio": "Was uns nicht umbringt, macht uns stärker.",
            "imgs": [],
            "content": "宿舍的事情，其实都是一句话，我忍你很久了。"
        },
        {
            "title": "《三体》中人列计算机是否有可能性？",
            "author": "白如冰",
            "bio": "闭关修炼",
            "imgs": [],
            "content": "你要有张艺谋。"
        },
        {
            "title": "你最尴尬的约会是怎样的？如何补救的？",
            "author": "葫芦哥",
            "bio": "一只产品汪",
            "imgs": [],
            "content": "大四找工作的时候，一妹子加我，后来聊得不错就去她学校玩了。当天走路总感觉裤子不对劲，去厕所，掏出一条秋裤来。"
        },
        {
            "title": "你听说过哪些误解？",
            "author": "筝弦 Cochan",
            "bio": "什么都不懂的逗比",
            "imgs": [],
            "content": "有个俄罗斯妹子和我说起中国。她说，中文真是异常难学，她的叔叔学了四年中文，到中国后发现还是一句话都听不懂。其实我在这次对话的半个月后才知道她叔叔在广州。"
        }
    ]
}