{
    "cover": "http://pic2.zhimg.com/78f618d2a8e505359f2370bb1f4e03df.jpg",
    "count": 4,
    "jokes": [
        {
            "title": "如何伪装成一位资深微软粉？",
            "author": "马力",
            "bio": "最美团队招聘中 http://hi.zuimeia.com/",
            "imgs": [],
            "content": "> "
        },
        {
            "title": "小说、动漫中「越古老，越强大」的逻辑是怎样形成的？",
            "author": "一袋猫粮",
            "bio": "大家讲道理嘛",
            "imgs": [],
            "content": "> 来源于现实——\r\n> 「你们真是我教过的所有学生中最差的一届。」\r\n> 可见人类就是越来越差。"
        },
        {
            "title": "珠宝鉴定师的日常工作是怎样的？",
            "author": "一只姐",
            "bio": "逗比设计师",
            "imgs": [],
            "content": "> 「这是假的。」\r\n> 「真的假的？」\r\n> 「真的。」\r\n> 「到底真的假的？」\r\n> 「真的是假的。」"
        },
        {
            "title": "脏话可以用什么语气词代替吗？",
            "author": "Phoenix小月",
            "bio": "是个好人，但不好惹。",
            "imgs": [],
            "content": "> "
        }
    ]
}