{
    "cover": "http://pic3.zhimg.com/9128105c65f768fa528efe9a9176ecd2.jpg",
    "count": 21,
    "jokes": [
        {
            "title": "妹子还书的时候夹了一张面巾纸，说明了什么？",
            "author": "Zzzwizard",
            "bio": "折叠区调查局副局长",
            "imgs": [],
            "content": "说明题主你对人家有意思。"
        },
        {
            "title": "没有女朋友是什么感受？",
            "author": "倪政",
            "bio": "一个积极向上的少年",
            "imgs": [],
            "content": "有一种怀才不遇的感觉-_-||"
        },
        {
            "title": "喜欢的男生的微博关注的都是一些大胸妹，有点无法接受，怎么办？",
            "author": "皓月丹心",
            "bio": "解放了自己的自由人",
            "imgs": [],
            "content": "他要全关注肌肉男你就更没有机会了。"
        },
        {
            "title": "有哪些很短却很悲伤的故事？",
            "author": "张金新",
            "bio": "学生，前端开发",
            "imgs": [],
            "content": "「你还记得她吗？」\r\n「早忘了，哈哈。」\r\n「我还没说是谁……」"
        },
        {
            "title": "直男是否真的认不出女朋友换没换眼影？",
            "author": "知乎用户",
            "bio": "科科，一道会答的都没有",
            "imgs": [],
            "content": "女生是不是真的看不出来这人越位了？"
        },
        {
            "title": "什么电影适合男女朋友单独看？",
            "author": "匿名用户",
            "bio": "",
            "imgs": [],
            "content": "在评论区广大知友的热心补充下，恩爱情侣、和睦夫妻必看电影更新到 3.0 版，~ o(*￣▽￣*)ブ撒花撒花，墙裂建议情侣们一起观看，可以让你们的感情更甜蜜哦：\r\n消失的爱人 Gone Girl\r\n温柔地杀我 Killing Me Softly\r\n大开眼界 Eyes Wide Shut\r\n危机四伏 What Lies Beneath\r\n本能 Basic Instinct\r\n美国丽人 American Beauty\r\n蓝色情人节 Blue Valentine\r\n其实你不懂他的心 He Is Just Not That Into You\r\n革命之路 Revolutionary Road"
        },
        {
            "title": "为什么第三者通常是女人？",
            "author": "休息",
            "bio": "转行达人～",
            "imgs": [],
            "content": "婚姻中出现女插足者，此女是第三者；\r\n出现男插足者，此妻子是红杏出墙。"
        },
        {
            "title": "跟情商低的人聊天是一种怎么样的体验？",
            "author": "田峰",
            "bio": "业余赛车手，逗比CEO",
            "imgs": [],
            "content": "想开除一个员工。遂发起对话如下：\r\n「你明天不用来上班了！」\r\n「哦，好。」\r\n第二天就没有来了。\r\n结果，第三天又来上班了。"
        },
        {
            "title": "你见过最让你无语的 cos 是怎样的？",
            "author": "微尘",
            "bio": "凡事太尽，缘分势必早尽。",
            "imgs": [],
            "content": "为了抓一个喜欢骚扰车震男女的精神病，一个男的戴上假发和另一个男的在车里摇车。"
        },
        {
            "title": "如何回答「你喜欢我什么」？",
            "author": "我就是月下",
            "bio": "",
            "imgs": [],
            "content": "这个不是有公式的吗？\r\n一个时间点 + 一件小事 + 形容润色 + 海誓山盟\r\n如：四年前的一个早上，你忙碌着为我准备早餐，看着你的身影，我恍惚看到了天使，美极了，那时我便默默对自己说，这就是我要用一辈子去爱去疼的人。\r\n最后紧紧抱住，不用多解释。"
        },
        {
            "title": "有些新水池本来没有鱼，为什么过一段时间就会有小鱼？它们来源是什么？",
            "author": "知乎用户",
            "bio": "著名节操爆表星人/污妖王",
            "imgs": [],
            "content": "物业放进去的。"
        },
        {
            "title": "你是从哪个细节发现女朋友出轨的？",
            "author": "北在北冥victor",
            "bio": "头颈外科硕士/心理医生",
            "imgs": [],
            "content": "麻蛋，10086 竟然知道她醉酒然后主动要求去接她。"
        },
        {
            "title": "有一个稀有的姓是一种怎样的感受？",
            "author": "张大民",
            "bio": "享受政治局特殊津贴！ 相声理论家，老北京化学所民科，业余教师",
            "imgs": [],
            "content": "大学班主任汪老师是个 60 来岁的老头，有一天他给我发了个短信，我活活乐了一天：\r\n请到我办公室来一趟汪。"
        },
        {
            "title": "哪个学校的网站首页最好看？",
            "author": "康凯",
            "bio": "程序猿",
            "imgs": [
                "http://pic3.zhimg.com/70/fd82ee90ecf05200a8950eb45a6ada76_b.jpg",
                "http://pic2.zhimg.com/70/02d5c9d3f3918354552f1629e120a875_b.jpg"
            ],
            "content": "都闪开，怒答一记。 (╯‵□′)╯︵┻━┻\r\n最高票答案里有人大官网晒女神的，\r\n哼！这就是你们人大的特色吗？\r\n你们人大妹子都这么好看吗？\r\n我们可不一样，我们向来求实求真，\r\n我们给众人呈现最具校园特色的一面，\r\n我们用真实而普通的日常情景装点官网！\r\n我们的官网才是最接地气的！\r\n来，哥哥别理她，我们继续谈笑风生。 ( ◔◡◔) (︶.̮︶✽)"
        },
        {
            "title": "你遇到过最糟糕的追求方式是什么？",
            "author": "浅野早苗",
            "bio": "INTP，铲贫锦鲤，深夜答题清晨匿。",
            "imgs": [
                "http://pic3.zhimg.com/70/d7ec9aeb8b0e66a3d640426d2cabc466_b.jpg"
            ],
            "content": "给我看了他给全班女生的评分表…\r\n包括家境、颜值、情史、性格、学习好坏、聪明程度、兴趣爱好、人际关系这些…分值精确到小数点后两位，还给我讲他的加权是怎么考虑的，密密麻麻一大张。\r\n他 可 高 兴 了 告 诉 我 我 被 选 中 了\r\n后面再遇到什么样我都已经淡定了。"
        },
        {
            "title": "世界上存在动漫少女般完美的身体吗？",
            "author": "匿名用户",
            "bio": "",
            "imgs": [
                "http://pic3.zhimg.com/70/5069995fff57677b958ca4f4b79264e6_b.jpg"
            ],
            "content": "真有这样的你敢要？？....."
        },
        {
            "title": "男人为什么不喜欢真正对他好的女人，却喜欢事儿多耍性子的女人？",
            "author": "庄野马",
            "bio": "机械工程师，失败人士",
            "imgs": [],
            "content": "题主你要明白：霍金能当物理学家，并不是因为他瘫痪…………"
        },
        {
            "title": "90 后的「门当户对」观念会消失吗？",
            "author": "可达鸭",
            "bio": "公众号：大青果药丸",
            "imgs": [],
            "content": "现在不叫「门不当户不对」了，改叫「三观不合」。"
        },
        {
            "title": "怎么在外给男朋友面子？",
            "author": "东南偏北",
            "bio": "白天有说有笑，晚上睡个好觉。用不正经的态度端正的活。",
            "imgs": [],
            "content": "同学聚会有一次一起玩真心话大冒险。\r\n朋友问女朋友。有没有车震过。\r\n女朋友回答有。\r\n我心里想女朋友真给我面子。没有在同学面前暴露出我没有车。"
        },
        {
            "title": "如何回答女友「谁更漂亮」的问题？",
            "author": "匿名用户",
            "bio": "",
            "imgs": [],
            "content": "逛街中。\r\n女：哎，那女生好漂亮！你说，我和她谁好看？\r\n男：想听真话还是假话？\r\n女：真话呗。\r\n男：你好看。\r\n女：假话呢？\r\n男：什么妹子？我没看到。"
        },
        {
            "title": "你妈觉得你嫁不出去是一种什么样的体验？",
            "author": "安雅",
            "bio": "微信公众号：ayat_12oaks",
            "imgs": [],
            "content": "我老公最近一直坐某产品的顺风车上下班，有一天回来后跟我讲了个笑话。\r\n话说他打到的顺风车司机是一个大叔，后座坐了个姑娘。由于顺风车可以拼车，他以为是拼车的，没注意，坐了副驾驶。上车后大叔跟他拉了半天家常，然后提了个问题：\r\n「小伙子，你结婚了吗？单身吗？后座那是我女儿，还单身，你要单身不介意，可以跟她交个朋友。」\r\n然后略微尴尬地说，女儿在某公司当设计师，年纪不小了，但是因为工作比较忙圈子比较小，又不善交际，一直找不到男朋友。爸妈一合计，干脆开车上下班接送的时候拉个顺风车，专拉男士，然后看着差不多的又没带婚戒就问一问。\r\n我听了简直 shock 掉。爹妈觉得你嫁不出去是一种什么样的体验？这姑娘是每天上下班都要跟陌生人相亲的体验……"
        }
    ]
}