{
    "cover": "http://pic4.zhimg.com/b75a8dc06c24cd094da19cfff2896d8b.jpg",
    "count": 4,
    "jokes": [
        {
            "title": "汉语中「量词」存在的意义是什么？",
            "author": "钱晋翔",
            "bio": "无节操的知道分子",
            "imgs": [],
            "content": "> 「有一条腿」和「有一腿」能一样？"
        },
        {
            "title": "100 字内能写出什么样的讽刺故事？",
            "author": "蹦蹦跳跳的菊花信",
            "bio": "",
            "imgs": [],
            "content": "> 时光机\r\n> 小王买了一架时光机，由于科技限制，时光机只能带他回到死前一分钟的时候。小王年仅二十，未婚单身，想到未来或许已走上人生巅峰，死前一定有众多显贵前来探望，再不济也能看到自己儿女的成就，想到此处，不禁心痒难耐。\r\n> 坐进时光机，只听得提示音道：「您好，请绑好安全带。」\r\n> 「是了，一会机器以光速运行，要固定好自己。」\r\n> 「您好，请关闭手机。」\r\n> 「是了，坐飞机还要飞行模式呢。」\r\n> 小王想到即将看到未来的自己，连按开始按钮的手都颤抖了。\r\n> 「您好，距离时光机爆炸还有 60 秒。」"
        },
        {
            "title": "吃鲱鱼罐头到底是怎样一种体验？",
            "author": "铁衣",
            "bio": "心累神教",
            "imgs": [],
            "content": "> 这是我朋友给我讲的故事。\r\n> 她在英国时跟一群人在同学家院子里开 party，中途食物告急，就让一位（忘了是哪国的）同学去厨房帮她拿 tuna 罐头来。\r\n> 异国同学不知道是没听懂还是没看懂，从厨房里翻出了几个看起来有点高级的罐头，由于她不确定拿没拿对，就直接打开了。\r\n> 我朋友说，这玩意儿罐头上写明了开启时要进行防护措施，要在上风口开。\r\n> 懵懂无知的同学打开罐头的一瞬间就手脚失灵，把内容物全洒在了自己身上。\r\n> 然后她惨叫着狂奔出房间冲进人群然后毅然跳进了花园里的水池。\r\n> 被她撞到的人也沾上了罐头里的东西，也惨叫着跟着跳进水池。\r\n> 以上的一切都发生在半分钟内。\r\n> ……我朋友说，在恶臭、惨叫、骚乱爆发的那一刻，她第一反应是以为丧尸潮爆发了。"
        },
        {
            "title": "吃瑞典的鲱鱼罐头配崂山白花蛇草水是一种怎样的体验？",
            "author": "有一只船",
            "bio": "懒王",
            "imgs": [],
            "content": "> 这应该是一道送命题……"
        }
    ]
}