{
    "cover": "http://pic4.zhimg.com/2d0cf3a3e930178a1b2bdcb502ad318f.jpg",
    "count": 4,
    "jokes": [
        {
            "title": "你见过最丑的设计是什么？",
            "author": "匿名用户",
            "bio": "",
            "imgs": [
                "https://pic2.zhimg.com/96b0135f136dbd968a38a5a0df4d8d8c_b.jpg"
            ],
            "content": "> 有一种设计叫丑到过目难忘。\r\n> 我已经被个甲方选定方案深深的折服了。\r\n> 这才叫牛逼。"
        },
        {
            "title": "你见过最丑的设计是什么？",
            "author": "伍叉叉",
            "bio": "大大大大蘑菇君",
            "imgs": [
                "https://pic2.zhimg.com/e60ba548e775022e6cdc8871f739b91a_b.jpg"
            ],
            "content": "> 我一直没舍得删，你们感受一下……"
        },
        {
            "title": "你见过最丑的设计是什么？",
            "author": "胡思乱想的VICKY",
            "bio": "HCer TJer",
            "imgs": [
                "http://pic1.zhimg.com/70/35640c89d1def42fda19b0939165fd80_b.jpg"
            ],
            "content": "> 你难道没有被这灵动的眼神打动？\r\n> 学海无涯之猛龙过江。"
        },
        {
            "title": "你见过最丑的设计是什么？",
            "author": "发条橘子667",
            "bio": "一个脱离了高级趣味的人。",
            "imgs": [],
            "content": "> 以前买过一个山寨充电器，这个充电器已经被我扔了，所以没法上图。\r\n> 我只能用生动的语言给大家描述下。\r\n> 那天我的手机充电器坏掉了，由于手头没有备用的于是打算去街边买一个山寨的临时用。\r\n> 地摊上的充电器琳琅满目，我一眼就挑中一个纯黑的。\r\n> 朴素，低调，直男基本款充电器。\r\n> 然而回家插上电之后我才发现这个看似朴实的直男充电器有着丰富的内心世界，自带一排闪来闪去的粉红色 LED 跑马灯。\r\n> 关！\r\n> 不！\r\n> 掉！\r\n> 雾操这背后浓浓的科技含量，你们感受下。\r\n> 我心想它闪去吧，魔性点就魔性点，反正我就临时用，有空就去买个原厂的。\r\n> 然而准备睡觉的时候我发现了一个更严重的问题。在关了灯之后这排粉红色小灯不仅亮的我要瞎了，还把我的房间营造出一种牛郎店的感觉。\r\n> 这要是被我室友看见还得了？\r\n> 这排灯究竟是多亮呢，我毫不夸张的说，如果它不闪，我有信心在这个充电器旁边看完一套《天龙八部》。\r\n> 太低碳了。\r\n> 而且由于这个充电器和我的插线板插口不兼容所以我只能把它插在墙上。所以我也就没办法在上面盖点东西遮光。后来我在上面挂了一条毛巾，虽然根本遮不住不过好歹能暗一点。\r\n> 最后我勉强坚持睡着了之后，凌晨三四点左右。大概是充电充满了，这个玩意儿突然自己响了，自动播放了一首：\r\n> 友谊地久天长。"
        }
    ]
}