{
    "cover": "https://pic3.zhimg.com/v2-2bcf9389bdede132977c75169460ea6a.jpg",
    "count": 4,
    "jokes": [
        {
            "title": "中国家长有哪些不可理喻的神逻辑？",
            "author": "晴夕",
            "bio": "写手/传媒",
            "imgs": [],
            "content": "> 小时候我跟我爸吵架，他作势要打我。\r\n> 我怒吼：你知不知道未成年人保护法！！我受法律保护的！！\r\n> 我爸冷笑一声：未成年人保护法只保护成绩好的小孩！\r\n> 我：……\r\n> 卒。"
        },
        {
            "title": "中国家长有哪些不可理喻的神逻辑？",
            "author": "路名德",
            "bio": "隐隐古代人",
            "imgs": [],
            "content": "> 就上个月我爸给我打电话。\r\n> 爸：大三都结束了，为啥还不找女朋友？\r\n> 我：我说了没人看的上我啊……\r\n> 爸：瞎说！你长那么帅，怎么可能没人看的上你！\r\n> 我：……我怎么不觉得我帅？\r\n> 爸：你是我的儿子，怎么可能不帅！"
        },
        {
            "title": "中国家长有哪些不可理喻的神逻辑？",
            "author": "黑莲花教主",
            "bio": "坐等《大话西游之爱你一万年》和《谈判官》上映的无聊浪一枚",
            "imgs": [],
            "content": "> 前两年一件事，我笑了很久。\r\n> 故事背景是，我和 W 是同班同学，我们妈妈恰好又是闺密，我们俩经常被放在一起比较。\r\n> 那天，两位妈妈交流完思想感情和育儿经，回到家，我妈看到我在看书，很生气：「又在看小说，不是不让你看，每天看书会把脑子看傻的，你就不能学学 W，多出去逛逛？」\r\n> 我默默放下书，拿起手机，把这件事告诉了 W。那头的 W 隔了三分钟才回我，她说，她正准备出门逛逛，刚在换鞋子，现在被她妈妈拦住了，她妈让她多学学我，窝在家里看书。"
        },
        {
            "title": "中国家长有哪些不可理喻的神逻辑？",
            "author": "不要问名字",
            "bio": "汽车制造/产品设计师/登山爱好者......我都不是！",
            "imgs": [],
            "content": "> 中国家长哪有什么不可理喻的神逻辑，还不都是为了你好。"
        }
    ]
}