{
    "cover": "https://pic1.zhimg.com/v2-77b3a10cc2bf548f8b0945f733ce4f48.jpg",
    "count": 4,
    "jokes": [
        {
            "title": "士大夫和 staff 有关系吗，感觉发音有点像哎？",
            "author": "知乎用户",
            "bio": "Kebab餐廳侍應生，Paris store雜工",
            "imgs": [],
            "content": "苏轼和 sushi 有什么关系？"
        },
        {
            "title": "电影《海王》有哪些槽点？",
            "author": "熊猫头的爸爸",
            "bio": "",
            "imgs": [],
            "content": "那个反派奥姆真的太惨了。刚出生没多久知道母亲出轨而被处死，然后后来父亲也死了。然后一个一次都没来过海底的大哥回来跟自己抢王位，身边的谋士和未婚妻都背叛了自己，然后又被大哥打败了，最后终于见到了原来没死的母亲，结果母亲告诉他她也支持大哥……"
        },
        {
            "title": "猫可以猥琐到什么程度？",
            "author": "刘中阳",
            "bio": "有电脑，有网络，就毁了……",
            "imgs": [
                "http://pic4.zhimg.com/70/v2-6ad97af97d00574b0f12835eaa635bcf_b.jpg"
            ],
            "content": ""
        },
        {
            "title": "一般什么样的人会开或者买劳斯莱斯？",
            "author": "Ggggg",
            "bio": "分离工程",
            "imgs": [],
            "content": "今年公司赚了 1000 万，要交 250 万的企业所得税，剩 750 万，要进私人口袋，再要交 20%的个人所得税，剩 600 万。\r\n大笔一挥，买两台劳斯莱斯。然后马上抵押给银行 / 金融机构，贷出来 800 万，银行利率低些，8%，但是钱要进公司账户。金融机构高些，年利率 12%多，但是有些可以进私人口袋。\r\n车计入资产，每年折旧抵扣（话说最近新规定好像 500 万以下都可以进成本），800 万变负债。每年可以开一堆保养发票，进成本。虽然有利息，但是比交 400 万税划算多了。\r\n还可以用来泡妹子。"
        }
    ]
}