{
    "cover": "https://pic4.zhimg.com/v2-20b63ae083218d40e29adbe646debe87.jpg",
    "count": 4,
    "jokes": [
        {
            "title": "你经历或你听过最奇葩的住院理由有哪些？",
            "author": "鸡茸蘑菇酒",
            "bio": "治病救兽",
            "imgs": [],
            "content": "动物医院。\r\n某天来了一只蓝猫，主人就是说他病了，要全身检查。检查下来啥事儿没有，主人说要住院。\r\n原因是，主人觉得他家蓝猫不举.....据说是被第一次配种的小母猫嫌弃了，然后就郁郁寡欢，什么猫都提不起兴趣……（可能雄性尊严被侵犯了……）\r\n住院是因为……想看看住院那么多猫有没有能让它重振雄风的。"
        },
        {
            "title": "你经历或你听过最奇葩的住院理由有哪些？",
            "author": "紫菀",
            "bio": "",
            "imgs": [],
            "content": "不请自来。实习的时候在 ICU，有一天晚上有个年轻男士从急诊送入科室，多处骨折，问他本人怎么搞的，他说把车停在坡上，下车后忘了拉手刹，车往下滑，后面还停了一辆车，想用自己的力量顶住，结果被两辆车挤在中间了。\r\n这是遇到的心酸又有点奇葩的住院经历了。"
        },
        {
            "title": "你经历或你听过最奇葩的住院理由有哪些？",
            "author": "皮克尼嘟噜嘟",
            "bio": "重症监护室傻狍子",
            "imgs": [],
            "content": "某老太太在医院输液，病情安稳，神态安详，儿子在旁护理，发现固定鼻周吸氧管的胶布有根线头，儿子就点了打火机去燎线头……据说现场是腾起一团火……然后老太太就以颜面烧伤、气道灼伤转到 ICU 了。后来儿子也来看望，双手缠着厚厚的纱布 7ಥ_ಥ"
        },
        {
            "title": "你经历或你听过最奇葩的住院理由有哪些？",
            "author": "Ash葛",
            "bio": "英国某正规高校英语最稀烂毕业生保持者",
            "imgs": [],
            "content": "高中一学弟，打球摔断了左手和右腿，所以每天他妈妈推着轮椅来送他上下学，在快好的时候，他妈妈推着轮椅来接他放学，我们学校门口有个巨长的下坡，他妈妈推轮椅时一把没有稳住，把他怂进了学校门口下水道的施工坑里，这下好了，右手和两条腿都断了。达成成就四肢全断，获得奖励住院，休学一年。\r\n虽然我已经毕业六年，虽然我和这个学弟关系不错，但是这个故事仍然让我们笑了他六年……\r\n「这个事让我深刻领会了陈佩斯的一句话“伟大喜剧的内核永远是悲剧」。"
        }
    ]
}