{
    "cover": "https://pic2.zhimg.com/v2-9e4ab3b268cf3db9ca2cd6ada80e2235.jpg",
    "count": 4,
    "jokes": [
        {
            "title": "可以成立一家皮包公司上市圈钱吗？",
            "author": "知乎用户",
            "bio": "求知欲忽强忽弱",
            "imgs": [],
            "content": "> 可以啊，LV 这不是做得挺成功吗。"
        },
        {
            "title": "在创作小说的时候，你的女朋友会介意女主角的名字性格不是她么？",
            "author": "zek zeng",
            "bio": "是木筷子与纸袋",
            "imgs": [],
            "content": "> 施耐庵老先生的压力一定很大……"
        },
        {
            "title": "「当时随便说说的话，结果意外实现了」是一种怎样的体验？",
            "author": "饭遥",
            "bio": "Chuzpah",
            "imgs": [],
            "content": "> 高三的时候想去同济大学，于是在桌子上刻了 TJU。\r\n> 后来到了天津大学。"
        },
        {
            "title": "怎样在朋友圈晒娃不让人烦？",
            "author": "混沌椰子王",
            "bio": "我和世界皆不完美。",
            "imgs": [],
            "content": "> 我去，儿子又在吃屎了。\r\n> 唉我去，儿子把我手机扔水里了。\r\n> 唉玛我去，儿子脑袋卡到马桶里了。"
        }
    ]
}